journ/__init__.py
journ-0.1.7.dist-info/METADATA
journ-0.1.7.dist-info/WHEEL
journ-0.1.7.dist-info/entry_points.txt
journ-0.1.7.dist-info/top_level.txt
journ-0.1.7.dist-info/RECORD
