Metadata-Version: 2.1
Name: journ
Version: 0.1.7
Summary: A really simple command line journal.
Home-page: https://github.com/ronbecker/journ
Author: Ron Becker
Author-email: ronbecker@outlook.com
License: UNKNOWN
Platform: UNKNOWN
Classifier: Programming Language :: Python :: 3
Classifier: License :: OSI Approved :: MIT License
Classifier: Operating System :: OS Independent
Classifier: Development Status :: 5 - Production/Stable
Requires-Python: >=3.6
